pydantic_containers/__init__.py
pydantic_containers-0.0.1.dist-info/METADATA
pydantic_containers-0.0.1.dist-info/WHEEL
pydantic_containers-0.0.1.dist-info/RECORD
