Metadata-Version: 2.1
Name: pydantic-containers
Version: 0.0.1
Summary: Serializable containers of pydantic models.
Author: Aditya Gudimella
Author-email: aditya.gudimella@gmail.com
Requires-Python: >=3.10,<4.0
Classifier: Programming Language :: Python :: 3
Classifier: Programming Language :: Python :: 3.10
Classifier: Programming Language :: Python :: 3.11
